rdf2gnn/__init__.py
rdf2gnn/main.py
rdf2gnn/utils.py
rdf2gnn-0.1.1.dist-info/METADATA
rdf2gnn-0.1.1.dist-info/WHEEL
rdf2gnn-0.1.1.dist-info/top_level.txt
rdf2gnn-0.1.1.dist-info/RECORD
